aniya/__init__.py
aniya/err.py
aniya/g.py
aniya/log.py
aniya/decorators/__init__.py
aniya/decorators/base.py
aniya/decorators/callback.py
aniya/decorators/compare.py
aniya/decorators/default.py
aniya/decorators/digits.py
aniya/decorators/exclude.py
aniya/decorators/include.py
aniya/decorators/keywords.py
aniya/decorators/length.py
aniya/decorators/regex.py
aniya/decorators/required.py
aniya/decorators/trans.py
aniya/utils/__init__.py
aniya/utils/tpc.py
aniya/utils/undefined.py
aniya/view/__init__.py
aniya/view/verify.py
test/__init__.py
test/decorators/__init__.py
test/decorators/test_verify_callback.py
test/decorators/test_verify_compare.py
test/decorators/test_verify_default.py
test/decorators/test_verify_digits.py
test/decorators/test_verify_exclude.py
test/decorators/test_verify_include.py
test/decorators/test_verify_keywords.py
test/decorators/test_verify_length.py
test/decorators/test_verify_regex.py
test/decorators/test_verify_required.py
test/decorators/test_verify_trans.py
aniya-1.0.0rc1.dist-info/LICENSE
aniya-1.0.0rc1.dist-info/METADATA
aniya-1.0.0rc1.dist-info/WHEEL
aniya-1.0.0rc1.dist-info/top_level.txt
aniya-1.0.0rc1.dist-info/RECORD
