Metadata-Version: 2.1
Name: aniya
Version: 1.0.0rc1
Summary: aniya is a compact, simple defined parameter check package.
Home-page: https://github.com/xccx0823/aniya
Author: cheer
Author-email: cheerxiong0823@163.com
Classifier: Programming Language :: Python :: 3
Classifier: License :: OSI Approved :: MIT License
Classifier: Operating System :: OS Independent
License-File: LICENSE
